gizmos/__init__.py
gizmos/check.py
gizmos/export.py
gizmos/extract.py
gizmos/helpers.py
gizmos/hiccup.py
gizmos/search.py
gizmos/tree.py
ontodev_gizmos-0.3.2.dist-info/LICENSE
ontodev_gizmos-0.3.2.dist-info/METADATA
ontodev_gizmos-0.3.2.dist-info/WHEEL
ontodev_gizmos-0.3.2.dist-info/top_level.txt
ontodev_gizmos-0.3.2.dist-info/RECORD
