Metadata-Version: 2.1
Name: ontodev-gizmos
Version: 0.3.2
Summary: Gizmos for ontology development
Home-page: UNKNOWN
Author: James A Overton
Author-email: james@overton.ca
License: UNKNOWN
Platform: UNKNOWN
Classifier: Programming Language :: Python :: 3
Classifier: Operating System :: OS Independent
Classifier: License :: OSI Approved :: BSD License
License-File: LICENSE
Requires-Dist: rdflib-jsonld
Requires-Dist: SQLAlchemy
